{"version":3,"kind":"Notebook","sha256":"465b56e0a9236e8db9787ed947a9591d023ba19f2e3d29d7e16e379b6e160196","slug":"new-notebook","location":"/notebooks/analysis/new_notebook.ipynb","dependencies":[],"frontmatter":{"title":"Testing Markdown","content_includes_title":true,"kernelspec":{"name":"python3","display_name":"quantum","language":"python"},"github":"https://github.com/Arthor1127/polaritons","numbering":{"title":{"offset":2}},"source_url":"https://github.com/Arthor1127/polaritons/blob/main/notebooks/analysis/new_notebook.ipynb","edit_url":"https://github.com/Arthor1127/polaritons/edit/main/notebooks/analysis/new_notebook.ipynb","exports":[{"format":"ipynb","filename":"new_notebook.ipynb","url":"/build/new_notebook-1e1fb0da6c340a0b01fd03220031e70a.ipynb"}]},"widgets":{},"mdast":{"type":"root","children":[{"type":"block","kind":"notebook-code","children":[{"type":"code","lang":"python","executable":true,"value":"import numpy as np\nimport matplotlib.pyplot as plt","key":"Vu4KiuitTN"},{"type":"outputs","id":"U7LRSca6k4WJwDnP2Zm4j","children":[],"key":"Uab25O9rUw"}],"key":"DfPdVdPTwp"},{"type":"block","kind":"notebook-content","children":[{"type":"heading","depth":1,"position":{"start":{"line":1,"column":1},"end":{"line":1,"column":1}},"children":[{"type":"text","value":"Testing Markdown","position":{"start":{"line":1,"column":1},"end":{"line":1,"column":1}},"key":"BDT4lZiNIN"}],"identifier":"testing-markdown","label":"Testing Markdown","html_id":"testing-markdown","implicit":true,"key":"QvLvOhKX9H"},{"type":"paragraph","position":{"start":{"line":2,"column":1},"end":{"line":2,"column":1}},"children":[{"type":"text","value":"This is something that works or not?","position":{"start":{"line":2,"column":1},"end":{"line":2,"column":1}},"key":"V33s5d3til"}],"key":"etQUHxT37A"}],"key":"Kt2Nbjeu6z"},{"type":"block","kind":"notebook-code","children":[{"type":"code","lang":"python","executable":true,"value":"#","key":"jb2jdQ5ANl"},{"type":"outputs","id":"f8U2aa1irxqzZTLBTihy-","children":[],"key":"xJxyf6pNY5"}],"key":"WCw6oz7WOe"}],"key":"v5hI6qn2LS"},"references":{"cite":{"order":[],"data":{}}},"footer":{"navigation":{"prev":{"title":"Two Site Resonant","url":"/two-site-resonant","group":"Exploration"},"next":{"title":"notes","url":"/readme-3","group":"Notes"}}},"domain":"http://localhost:3003"}